unifont_utils/__init__.py
unifont_utils/base.py
unifont_utils/console.py
unifont_utils/converter.py
unifont_utils/diff.py
unifont_utils/downloader.py
unifont_utils/editor.py
unifont_utils/editor.tcss
unifont_utils/glyphs.py
unifont_utils/page_converter.py
unifont_utils-0.6.4.dist-info/METADATA
unifont_utils-0.6.4.dist-info/WHEEL
unifont_utils-0.6.4.dist-info/entry_points.txt
unifont_utils-0.6.4.dist-info/licenses/LICENSE
unifont_utils-0.6.4.dist-info/RECORD
