Metadata-Version: 2.4
Name: unifont_utils
Version: 0.6.4
Summary: Unifont Utilities, but rewritten in Python.
Project-URL: Repository, https://github.com/SkyEye-FAST/unifont_utils
Author-email: SkyEye_FAST <skyeyefast@foxmail.com>
License-Expression: GPL-3.0-or-later
License-File: LICENSE
Keywords: unifont
Classifier: Development Status :: 4 - Beta
Classifier: Intended Audience :: Developers
Classifier: License :: OSI Approved :: GNU General Public License v3 or later (GPLv3+)
Classifier: Natural Language :: Chinese (Simplified)
Classifier: Natural Language :: English
Classifier: Programming Language :: Python :: 3.10
Classifier: Programming Language :: Python :: 3.11
Classifier: Programming Language :: Python :: 3.12
Classifier: Programming Language :: Python :: 3.13
Classifier: Programming Language :: Python :: 3.14
Classifier: Topic :: Text Processing :: Fonts
Classifier: Topic :: Utilities
Requires-Python: <4.0,>=3.10
Requires-Dist: click>=8.1.0
Requires-Dist: pillow>=10.0
Requires-Dist: requests>=2.31
Requires-Dist: textual>=0.80.0
